easy_pyttsx3/__init__.py
easy_pyttsx3-1.0.0.dist-info/LICENCE
easy_pyttsx3-1.0.0.dist-info/METADATA
easy_pyttsx3-1.0.0.dist-info/WHEEL
easy_pyttsx3-1.0.0.dist-info/top_level.txt
easy_pyttsx3-1.0.0.dist-info/RECORD
