Metadata-Version: 2.1
Name: easy-pyttsx3
Version: 1.0.0
Summary: This package can convert text to speeh in very easy way...
Home-page: UNKNOWN
Author: Akshat Tiwari
Author-email: thealphacoding@gmail.com
License: UNKNOWN
Platform: UNKNOWN
Classifier: Programming Language :: Python :: 3
Classifier: License :: OSI Approved :: MIT License
Classifier: Operating System :: OS Independent
Requires-Python: >=3.2
Requires-Dist: pyttsx3
